[
  {
    "timeLimit": "2초",
    "memoryLimit": "128MB",
    "question": "괄호 문자열은 다음과 같이 정의한다.\n1. 빈 문자열은 괄호 문자열이다.\n2. S가 괄호 문자열일 때, (S)도 괄호 문자열이다.\n3. S와 T가 괄호 문자열이면, ST도 괄호 문자열이다.\n\n길이가 N인 괄호 문자열 중 사전순으로 K번째인 괄호 문자열을 출력하시오. 존재하지 않으면 -1을 출력한다.",
    "input": "첫째 줄에 두 정수 N과 K가 주어진다.",
    "output": "조건을 만족하는 괄호 문자열 또는 -1을 출력한다.",
    "constraints": [
      "1 ≤ N ≤ 50",
      "0 ≤ K ≤ 2^N - 1"
    ],
    "testCases": [
      {
        "input": "2 0",
        "output": "()"
      },
      {
        "input": "2 1",
        "output": "-1"
      },
      {
        "input": "4 0",
        "output": "((()))"
      },
      {
        "input": "4 1",
        "output": "(()())"
      },
      {
        "input": "4 2",
        "output": "(())()"
      },
      {
        "input": "4 3",
        "output": "()(())"
      },
      {
        "input": "4 4",
        "output": "()()()"
      },
      {
        "input": "4 5",
        "output": "-1"
      },
      {
        "input": "6 0",
        "output": "(((())))"
      },
      {
        "input": "6 4",
        "output": "(()(()))"
      },
      {
        "input": "6 13",
        "output": "()()()()"
      },
      {
        "input": "6 14",
        "output": "-1"
      },
      {
        "input": "8 0",
        "output": "((((()))))"
      },
      {
        "input": "8 13",
        "output": "((())(()))"
      },
      {
        "input": "8 19",
        "output": "(()()(()))"
      },
      {
        "input": "8 42",
        "output": "-1"
      },
      {
        "input": "10 0",
        "output": "(((((())))))"
      },
      {
        "input": "10 10",
        "output": "(((()()())))"
      },
      {
        "input": "10 15",
        "output": "((()(()())))"
      },
      {
        "input": "10 42",
        "output": "((())()(()))"
      },
      {
        "input": "10 60",
        "output": "(()(()(())))"
      },
      {
        "input": "10 91",
        "output": "()()()()()"
      },
      {
        "input": "10 92",
        "output": "-1"
      },
      {
        "input": "12 0",
        "output": "((((((()))))))"
      },
      {
        "input": "12 10",
        "output": "(((((()())()))))"
      },
      {
        "input": "12 15",
        "output": "(((((())()()))))"
      },
      {
        "input": "12 30",
        "output": "(((()()(()()))))"
      },
      {
        "input": "12 50",
        "output": "((()(()(()()))))"
      },
      {
        "input": "12 91",
        "output": "(()()()()(()))"
      },
      {
        "input": "12 132",
        "output": "()()()()()()"
      },
      {
        "input": "12 133",
        "output": "-1"
      },
      {
        "input": "14 0",
        "output": "(((((((()))))))"
      },
      {
        "input": "14 10",
        "output": "((((((()())()))))"
      },
      {
        "input": "14 28",
        "output": "((((()()(()()))))"
      },
      {
        "input": "14 56",
        "output": "(((()(()(()()))))"
      },
      {
        "input": "14 91",
        "output": "((()()()()(())))"
      },
      {
        "input": "14 132",
        "output": "(()()()()()(()))"
      },
      {
        "input": "14 254",
        "output": "()()()()()()()"
      },
      {
        "input": "14 255",
        "output": "-1"
      },
      {
        "input": "16 0",
        "output": "((((((((()))))))))"
      },
      {
        "input": "16 5",
        "output": "(((((((()())()))))))"
      },
      {
        "input": "16 40",
        "output": "((((((()()(()()))))))"
      },
      {
        "input": "16 70",
        "output": "(((((())()(()()))))))"
      },
      {
        "input": "16 126",
        "output": "(((()()(()()(())))))"
      },
      {
        "input": "16 252",
        "output": "()()()()()()()()"
      },
      {
        "input": "16 253",
        "output": "-1"
      },
      {
        "input": "18 0",
        "output": "(((((((((()))))))))"
      },
      {
        "input": "18 5",
        "output": "((((((((()())()))))))"
      },
      {
        "input": "18 20",
        "output": "(((((((()()(()()))))))"
      },
      {
        "input": "18 42",
        "output": "((((((())()(()()))))))"
      },
      {
        "input": "18 92",
        "output": "((()()()(()()(())))))"
      },
      {
        "input": "18 132",
        "output": "(()()()()(()()(())))"
      }
    ]
  },
  {
    "timeLimit": "2초",
    "memoryLimit": "128MB",
    "question": "지민이는 수의 리스트가 있을 때, 이를 짝지어 각 쌍의 합이 소수가 되게 하려고 한다. 수의 리스트가 주어졌을 때, 지민이가 모든 수를 다 짝지었을 때, 첫 번째 수와 어떤 수를 짝지었는지 오름차순으로 출력하는 프로그램을 작성하시오. 없으면 -1을 출력한다.",
    "input": "첫째 줄에 리스트의 크기 N이 주어진다. N은 50보다 작거나 같은 자연수이며, 짝수이다. 둘째 줄에는 리스트에 들어있는 수가 주어진다.",
    "output": "첫째 줄에 정답을 출력한다. 없으면 -1을 출력한다.",
    "constraints": [
      "2 ≤ N ≤ 50",
      "입력되는 수는 1,000 이하의 자연수이며 중복되지 않음",
      "N은 짝수이다"
    ],
    "testCases": [
      {
        "input": "20\n955 304 482 135 262 997 191 932 640 643 755 54 737 722 880 999 219 638 269 684",
        "output": "54 955"
      },
      {
        "input": "46\n436 361 641 686 696 161 143 194 183 74 760 349 18 845 798 821 981 616 537 766 554 737 295 318 303 608 177 874 136 367 52 187 915 178 313 334 299 498 369 908 643 574 956 767 695 392",
        "output": "177 436"
      },
      {
        "input": "28\n256 163 144 287 235 358 37 454 640 447 900 41 476 233 845 248 198 893 901 846 664 165 554 243 103 778 438 25",
        "output": "25 256"
      },
      {
        "input": "26\n406 85 270 473 315 164 480 349 657 602 953 144 173 546 253 166 699 182 171 922 201 662 530 557 588 785",
        "output": "85 406"
      },
      {
        "input": "48\n324 197 617 830 374 537 737 624 453 770 256 363 369 754 820 343 317 650 626 803 878 723 257 840 910 639 525 158 64 39 749 548 662 11 918 683 563 356 517 580 869 864 381 472 293 704 953 656",
        "output": "197 324"
      },
      {
        "input": "40\n375 932 204 397 434 113 140 141 611 876 410 69 115 162 120 157 828 79 911 528 520 511 468 685 76 87 217 720 77 372 228 583 616 807 463 310 224 999 852 577",
        "output": "224 375"
      },
      {
        "input": "50\n146 717 47 614 664 919 343 78 598 913 233 368 289 64 471 730 780 449 460 157 740 473 428 999 111 880 839 462 379 274 36 751 657 926 654 409 746 975 876 781 627 796 853 846 13 160 725 512 347 506",
        "output": "47 146"
      },
      {
        "input": "24\n5 986 457 942 324 877 966 157 209 18 469 388 400 213 63 988 965 12 825 172 724 243 654 899",
        "output": "5 12"
      },
      {
        "input": "30\n447 14 464 659 545 608 775 922 154 13 924 383 209 768 755 296 692 761 749 320 186 917 136 981 255 316 327 964 427 142",
        "output": "14 447"
      },
      {
        "input": "6\n584 897 289 912 326 767",
        "output": "584 897"
      },
      {
        "input": "34\n782 927 813 934 131 752 81 646 648 673 506 597 695 66 404 833 87 854 750 529 36 751 948 169 790 439 332 285 475 364 166 291 639 932",
        "output": "81 782"
      },
      {
        "input": "30\n74 63 612 919 481 228 37 874 858 571 769 54 374 35 604 829 986 387 276 415 964 199 365 554 884 209 487 792 536 401",
        "output": "35 74"
      },
      {
        "input": "38\n596 683 910 489 245 786 366 221 457 46 852 619 287 96 977 56 387 566 436 717 160 573 916 741 550 567 236 305 83 524 36 707 391 52 373 258 606 833",
        "output": "287 596"
      },
      {
        "input": "28\n701 348 38 201 543 130 420 143 174 287 548 449 658 495 322 597 179 884 811 18 266 843 833 866 617 402 274 775",
        "output": "38 701"
      },
      {
        "input": "44\n14 433 702 358 646 451 34 946 406 556 324 375 295 62 330 84 157 83 615 619 938 133 702 492 576 564 308 535 406 818 49 360 40 929 679 336 757 848 140 595 911 456 943 194",
        "output": "14 433"
      },
      {
        "input": "26\n990 139 871 573 548 221 462 13 394 740 325 937 325 416 999 426 201 659 179 306 558 254 474 48 57 162",
        "output": "13 990"
      },
      {
        "input": "12\n116 893 56 793 469 227 720 91 494 131 48 805",
        "output": "48 893"
      },
      {
        "input": "10\n944 770 537 801 294 35 64 555 36 259",
        "output": "35 944"
      },
      {
        "input": "20\n865 702 207 82 634 989 502 274 535 463 789 367 879 469 916 26 47 830 764 677",
        "output": "47 82"
      },
      {
        "input": "22\n311 850 160 711 919 78 889 772 295 99 128 787 116 471 429 684 174 786 408 506 818 793",
        "output": "78 311"
      }
    ]
  },
  {
    "timeLimit": "2초",
    "memoryLimit": "128MB",
    "question": "DNA 문자열과 변환 테이블이 주어질 때, 가능한 서로 다른 단백질 개수를 구하시오.",
    "input": "첫째 줄에 DNA 문자열이 주어진다. 둘째 줄에는 코돈 변환 테이블에 들어있는 코돈의 개수 M이 주어진다. 다음 M줄에는 각 코돈과 아미노산이 주어진다.",
    "output": "서로 다른 단백질 개수를 1,000,000,007로 나눈 나머지를 출력한다.",
    "constraints": [
      "DNA 문자열 길이 ≤ 2500",
      "1 ≤ M ≤ 50",
      "코돈은 중복되지 않음"
    ],
    "testCases": [
      {
        "input": "ACTG\n4\nACT gua\nACG sys\nATG leu\nTGC lys",
        "output": "3"
      },
      {
        "input": "ACGTGGTACGTAGCTAGCTG\n5\nACG x\nTGG y\nTAC z\nGCT k\nAGC t",
        "output": "5"
      },
      {
        "input": "ACGACGACG\n2\nACG lys\nCGT pro",
        "output": "1"
      },
      {
        "input": "ACGTTGACGTTG\n4\nACG lys\nTTG val\nGTT met\nTGA end",
        "output": "3"
      },
      {
        "input": "GATTACA\n3\nGAT ala\nTAC leu\nACA ser",
        "output": "1"
      },
      {
        "input": "TACGGTACGTACGGTACG\n6\nTAC A\nGGT B\nACG C\nCGG D\nGTA E\nCGT F",
        "output": "8"
      },
      {
        "input": "CGCGCGCGCG\n2\nCGC x\nGCG y",
        "output": "2"
      },
      {
        "input": "TTTTTTTTT\n1\nTTT x",
        "output": "1"
      },
      {
        "input": "ACGTACGTACGT\n3\nACG x\nCGT y\nGTA z",
        "output": "4"
      },
      {
        "input": "ATGCCCTAG\n3\nATG start\nCCC pro\nTAG stop",
        "output": "1"
      },
      {
        "input": "AGTTCAGTTCAGTTC\n4\nAGT x\nTTC y\nCAG z\nGTT w",
        "output": "6"
      },
      {
        "input": "CCCCCCCCCC\n1\nCCC a",
        "output": "1"
      },
      {
        "input": "ACGTGACGTTGACGTGACG\n5\nACG A\nCGT B\nGAC C\nTTG D\nTGA E",
        "output": "7"
      },
      {
        "input": "GTAGTAGTA\n2\nGTA x\nTAG y",
        "output": "2"
      },
      {
        "input": "AACCGGTTAACCGGTT\n4\nAAC a\nCCG b\nGGT c\nTTA d",
        "output": "6"
      },
      {
        "input": "AGCTAGCTAGCTAGCT\n3\nAGC x\nGCT y\nCTA z",
        "output": "4"
      },
      {
        "input": "ATCGATCGATCG\n4\nATC a\nTCG b\nCGA c\nGAT d",
        "output": "5"
      },
      {
        "input": "GCGCGCGCGC\n2\nGCG m\nCGC n",
        "output": "2"
      },
      {
        "input": "TTATTATTATTATTATTATTA\n3\nTTA x\nTAT y\nATT z",
        "output": "4"
      },
      {
        "input": "ACGTACGTACGTACGT\n5\nACG p\nCGT q\nGTA r\nTAC s\nACT t",
        "output": "6"
      }
    ]
  },
  {
    "timeLimit": "1초",
    "memoryLimit": "512MB",
    "question": "N개의 수가 있는 X와 Y가 있다. 이때 X나 Y를 순환 이동시킬 수 있다. 순환 이동이란 마지막 원소를 제거하고 그 수를 맨 앞으로 다시 삽입하는 것이다.\n예를 들어, (1, 2, 3)을 순환 이동시키면 (3, 1, 2)가 될 것이다. 이때 X와 Y를 순환 이동시킨 후 다음 식으로 점수를 구한다:\nS = X[0]×Y[0] + X[1]×Y[1] + ... + X[N-1]×Y[N-1]\n이 점수 S를 최대로 만들면 된다.",
    "input": "첫째 줄에 정수 N이 주어진다. 둘째 줄에는 X에 들어있는 N개의 수가 주어진다. 셋째 줄에는 Y에 들어있는 N개의 수가 주어진다.",
    "output": "점수 S의 최대값을 출력한다.",
    "constraints": [
      "1 ≤ N ≤ 60000",
      "X와 Y의 각 원소는 0 이상 100 미만의 자연수 또는 0"
    ],
    "testCases": [
      {
        "input": "3\n1 2 3\n4 5 6",
        "output": "32"
      },
      {
        "input": "3\n3 2 1\n6 5 4",
        "output": "32"
      },
      {
        "input": "4\n1 1 1 1\n1 1 1 1",
        "output": "4"
      },
      {
        "input": "5\n1 2 3 4 5\n5 4 3 2 1",
        "output": "55"
      },
      {
        "input": "1\n5\n7",
        "output": "35"
      },
      {
        "input": "2\n1 100\n100 1",
        "output": "200"
      },
      {
        "input": "2\n0 0\n0 0",
        "output": "0"
      },
      {
        "input": "2\n0 1\n1 0",
        "output": "1"
      },
      {
        "input": "6\n5 10 15 20 25 30\n30 25 20 15 10 5",
        "output": "1075"
      },
      {
        "input": "6\n30 25 20 15 10 5\n5 10 15 20 25 30",
        "output": "1075"
      },
      {
        "input": "10\n1 2 3 4 5 6 7 8 9 10\n10 9 8 7 6 5 4 3 2 1",
        "output": "220"
      },
      {
        "input": "3\n1 0 1\n1 0 1",
        "output": "2"
      },
      {
        "input": "3\n0 1 0\n1 0 1",
        "output": "2"
      },
      {
        "input": "3\n100 0 100\n100 0 100",
        "output": "20000"
      },
      {
        "input": "3\n0 100 0\n0 100 0",
        "output": "10000"
      },
      {
        "input": "3\n100 100 100\n100 100 100",
        "output": "30000"
      },
      {
        "input": "3\n99 98 97\n1 2 3",
        "output": "686"
      },
      {
        "input": "3\n1 2 3\n99 98 97",
        "output": "686"
      },
      {
        "input": "5\n10 20 30 40 50\n1 2 3 4 5",
        "output": "550"
      },
      {
        "input": "5\n50 40 30 20 10\n1 2 3 4 5",
        "output": "550"
      },
      {
        "input": "6\n0 1 2 3 4 5\n5 4 3 2 1 0",
        "output": "35"
      },
      {
        "input": "4\n1 2 3 4\n4 3 2 1",
        "output": "30"
      },
      {
        "input": "4\n4 3 2 1\n1 2 3 4",
        "output": "30"
      },
      {
        "input": "4\n0 0 0 0\n1 2 3 4",
        "output": "0"
      },
      {
        "input": "4\n1 2 3 4\n0 0 0 0",
        "output": "0"
      },
      {
        "input": "2\n99 1\n1 99",
        "output": "198"
      },
      {
        "input": "2\n1 99\n99 1",
        "output": "198"
      },
      {
        "input": "2\n50 50\n50 50",
        "output": "5000"
      },
      {
        "input": "2\n50 49\n49 50",
        "output": "4901"
      },
      {
        "input": "6\n1 1 1 1 1 1\n1 1 1 1 1 1",
        "output": "6"
      },
      {
        "input": "6\n1 2 3 4 5 6\n6 5 4 3 2 1",
        "output": "91"
      },
      {
        "input": "6\n6 5 4 3 2 1\n1 2 3 4 5 6",
        "output": "91"
      },
      {
        "input": "3\n10 20 30\n30 20 10",
        "output": "1400"
      },
      {
        "input": "3\n30 20 10\n10 20 30",
        "output": "1400"
      },
      {
        "input": "5\n1 3 5 7 9\n9 7 5 3 1",
        "output": "165"
      },
      {
        "input": "5\n9 7 5 3 1\n1 3 5 7 9",
        "output": "165"
      },
      {
        "input": "3\n2 2 2\n2 2 2",
        "output": "12"
      },
      {
        "input": "3\n2 0 2\n2 0 2",
        "output": "8"
      },
      {
        "input": "3\n0 2 0\n0 2 0",
        "output": "4"
      },
      {
        "input": "3\n1 2 3\n3 2 1",
        "output": "14"
      },
      {
        "input": "3\n3 2 1\n1 2 3",
        "output": "14"
      },
      {
        "input": "4\n100 0 100 0\n0 100 0 100",
        "output": "20000"
      },
      {
        "input": "4\n0 100 0 100\n100 0 100 0",
        "output": "20000"
      },
      {
        "input": "2\n1 1\n1 1",
        "output": "2"
      },
      {
        "input": "2\n0 1\n1 0",
        "output": "1"
      },
      {
        "input": "2\n1 0\n0 1",
        "output": "1"
      },
      {
        "input": "1\n0\n100",
        "output": "0"
      },
      {
        "input": "1\n100\n0",
        "output": "0"
      },
      {
        "input": "1\n100\n100",
        "output": "10000"
      },
      {
        "input": "1\n99\n99",
        "output": "9801"
      }
    ]
  },
  {
    "timeLimit": "2초",
    "memoryLimit": "128MB",
    "question": "어떤 수 X의 자릿수를 A개의 연속된 그룹으로 나누었을 때, 각 그룹의 자릿수가 등차수열이면 그 수를 A한수라고 한다. 만약 어떤 양의 정수가 A-1한수가 아닐 때, 그리고 그 수의 자릿수가 비내림차순일 때, 그 수를 진짜 A한수라고 한다.\nN과 A가 주어질 때, N자릿수이면서 진짜 A한수의 개수를 구하시오. (가장 첫 수는 0이 아니다)",
    "input": "첫째 줄에 정수 N과 A가 주어진다.",
    "output": "N자릿수이면서 진짜 A한수의 개수를 1,000,000,007로 나눈 나머지를 출력한다.",
    "constraints": [
      "1 ≤ N ≤ 1000",
      "1 ≤ A ≤ N"
    ],
    "testCases": [
      {
        "input": "2 2",
        "output": "81"
      },
      {
        "input": "3 2",
        "output": "243"
      },
      {
        "input": "3 3",
        "output": "36"
      },
      {
        "input": "4 2",
        "output": "513"
      },
      {
        "input": "4 3",
        "output": "216"
      },
      {
        "input": "4 4",
        "output": "9"
      },
      {
        "input": "5 2",
        "output": "1053"
      },
      {
        "input": "5 3",
        "output": "621"
      },
      {
        "input": "5 4",
        "output": "180"
      },
      {
        "input": "5 5",
        "output": "9"
      },
      {
        "input": "6 2",
        "output": "1701"
      },
      {
        "input": "6 3",
        "output": "1233"
      },
      {
        "input": "6 4",
        "output": "585"
      },
      {
        "input": "6 5",
        "output": "108"
      },
      {
        "input": "6 6",
        "output": "9"
      },
      {
        "input": "7 2",
        "output": "2601"
      },
      {
        "input": "7 3",
        "output": "2052"
      },
      {
        "input": "7 4",
        "output": "1296"
      },
      {
        "input": "7 5",
        "output": "441"
      },
      {
        "input": "7 6",
        "output": "72"
      },
      {
        "input": "7 7",
        "output": "9"
      },
      {
        "input": "8 2",
        "output": "3699"
      },
      {
        "input": "8 3",
        "output": "3168"
      },
      {
        "input": "8 4",
        "output": "2268"
      },
      {
        "input": "8 5",
        "output": "1134"
      },
      {
        "input": "8 6",
        "output": "324"
      },
      {
        "input": "8 7",
        "output": "54"
      },
      {
        "input": "8 8",
        "output": "9"
      },
      {
        "input": "9 2",
        "output": "5103"
      },
      {
        "input": "9 3",
        "output": "4599"
      },
      {
        "input": "9 4",
        "output": "3645"
      },
      {
        "input": "9 5",
        "output": "2430"
      },
      {
        "input": "9 6",
        "output": "1125"
      },
      {
        "input": "9 7",
        "output": "270"
      },
      {
        "input": "9 8",
        "output": "45"
      },
      {
        "input": "9 9",
        "output": "9"
      },
      {
        "input": "10 2",
        "output": "6849"
      },
      {
        "input": "10 3",
        "output": "6372"
      },
      {
        "input": "10 4",
        "output": "5400"
      },
      {
        "input": "10 5",
        "output": "4050"
      },
      {
        "input": "10 6",
        "output": "2430"
      },
      {
        "input": "10 7",
        "output": "1080"
      },
      {
        "input": "10 8",
        "output": "315"
      },
      {
        "input": "10 9",
        "output": "36"
      },
      {
        "input": "10 10",
        "output": "9"
      },
      {
        "input": "11 2",
        "output": "8955"
      },
      {
        "input": "11 3",
        "output": "8463"
      },
      {
        "input": "11 4",
        "output": "7560"
      },
      {
        "input": "11 5",
        "output": "6210"
      },
      {
        "input": "11 6",
        "output": "4590"
      },
      {
        "input": "11 7",
        "output": "2835"
      },
      {
        "input": "11 8",
        "output": "1260"
      },
      {
        "input": "11 9",
        "output": "315"
      },
      {
        "input": "11 10",
        "output": "27"
      },
      {
        "input": "11 11",
        "output": "9"
      }
    ]
  }
]
